ldp_toolbox/protocols/base.py
ldp_toolbox/protocols/frequency/grr.py
ldp_toolbox/protocols/frequency/he.py
ldp_toolbox/protocols/frequency/lh.py
ldp_toolbox/protocols/frequency/ss.py
ldp_toolbox/protocols/frequency/ue.py
ldp_toolbox/toolbox/app.py
ldp_toolbox/toolbox/assets/custom.css
ldp_toolbox/toolbox/assets/inria_logo_rouge.jpg
ldp_toolbox/toolbox/assets/logo-insa.jpg
ldp_toolbox/toolbox/pages/custom_upload.py
ldp_toolbox/toolbox/pages/style.py
ldp_toolbox/toolbox/pages/utils.py
ldp_toolbox/toolbox/pages/visualization.py
ldp_toolbox-0.1.3.dist-info/licenses/LICENSE
ldp_toolbox-0.1.3.dist-info/METADATA
ldp_toolbox-0.1.3.dist-info/WHEEL
ldp_toolbox-0.1.3.dist-info/entry_points.txt
ldp_toolbox-0.1.3.dist-info/top_level.txt
ldp_toolbox-0.1.3.dist-info/RECORD
