Metadata-Version: 2.4
Name: ldp-toolbox
Version: 0.1.3
Summary: Local Differential Privacy Toolbox
Author: Haoying Zhang, Abhishek K. Mishra, Héber H. Arcolezi
License: MIT License
Project-URL: Homepage, https://github.com/hharcolezi/ldp-toolbox
Project-URL: PyPI, https://pypi.org/project/ldp-toolbox/
Classifier: Programming Language :: Python :: 3
Classifier: License :: OSI Approved :: MIT License
Classifier: Operating System :: OS Independent
Requires-Python: >=3.8
License-File: LICENSE
Requires-Dist: dash>=2.18.2
Requires-Dist: dash-bootstrap-components>=1.7.1
Requires-Dist: numpy>=2.1.3
Requires-Dist: scipy>=1.15.2
Requires-Dist: matplotlib>=3.10.1
Requires-Dist: numba>=0.61.0
Requires-Dist: ray>=2.45.0
Requires-Dist: xxhash>=3.5.0
Requires-Dist: pandas>=2.3.0
Requires-Dist: tqdm>=4.67.1
Requires-Dist: joblib>=1.5.1
Provides-Extra: dev
Requires-Dist: pytest; extra == "dev"
Requires-Dist: black; extra == "dev"
Requires-Dist: flake8; extra == "dev"
Dynamic: license-file
